audio2anki/__init__.py
audio2anki/anki.py
audio2anki/artifact_cache.py
audio2anki/audio_utils.py
audio2anki/cache.py
audio2anki/config.py
audio2anki/exceptions.py
audio2anki/main.py
audio2anki/models.py
audio2anki/pipeline.py
audio2anki/select_sentences.py
audio2anki/transcoder.py
audio2anki/transcribe.py
audio2anki/translate.py
audio2anki/types.py
audio2anki/usage_tracker.py
audio2anki/utils.py
audio2anki/voice_isolation.py
audio2anki/resources/import_to_anki.sh
audio2anki-0.2.0.dist-info/METADATA
audio2anki-0.2.0.dist-info/WHEEL
audio2anki-0.2.0.dist-info/entry_points.txt
audio2anki-0.2.0.dist-info/licenses/LICENSE
audio2anki-0.2.0.dist-info/RECORD
